{
  "background": "",
  "foreground": "",
  "selectionBackground": "",
  "selectionForeground": "",
  "inactiveSelectionBackground": "",
  "selectionHighlightBackground": "",
  "selectionHighlightBorder": "",
  "wordHighlightBackground": "",
  "wordHighlightBorder": "",
  "wordHighlightStrongBackground": "",
  "wordHighlightStrongBorder": "",
  "findMatchBackground": "",
  "findMatchHighlightBackground": "",
  "findRangeHighlightBackground": "",
  "findMatchBorder": "",
  "findMatchHighlightBorder": "",
  "findRangeHighlightBorder": "",
  "hoverHighlightBackground": "",
  "lineHighlightBackground": "",
  "lineHighlightBorder": "",
  "rangeHighlightBackground": "",
  "rangeHighlightBorder": "",
  "symbolHighlightBackground": "",
  "symbolHighlightBorder": "",
  "guides": {
    "indentation": true,
    "highlightActiveIndentation": true
  },
  "inlineSuggest": {
    "enabled": true
  },
  "rulers": {},
  "linkedEditingBackground": "",
  "foldBackground": "",
  "stackFrameHighlightBackground": "",
  "focusedStackFrameHighlightBackground": "",
  "inlineValuesForeground": "",
  "inlineValuesBackground": "",
  "snippetTabstopHighlightBackground": "",
  "snippetTabstopHighlightBorder": "",
  "snippetFinalTabstopHighlightBackground": "",
  "snippetFinalTabstopHighlightBorder": ""
}
